odoo/addons/purchase_requisition_grouped_by_procurement/README.rst
odoo/addons/purchase_requisition_grouped_by_procurement/__init__.py
odoo/addons/purchase_requisition_grouped_by_procurement/__manifest__.py
odoo/addons/purchase_requisition_grouped_by_procurement/i18n/es.po
odoo/addons/purchase_requisition_grouped_by_procurement/i18n/purchase_requisition_grouped_by_procurement.pot
odoo/addons/purchase_requisition_grouped_by_procurement/models/__init__.py
odoo/addons/purchase_requisition_grouped_by_procurement/models/purchase_requisition.py
odoo/addons/purchase_requisition_grouped_by_procurement/models/stock_rule.py
odoo/addons/purchase_requisition_grouped_by_procurement/readme/CONFIGURE.rst
odoo/addons/purchase_requisition_grouped_by_procurement/readme/CONTRIBUTORS.rst
odoo/addons/purchase_requisition_grouped_by_procurement/readme/DESCRIPTION.rst
odoo/addons/purchase_requisition_grouped_by_procurement/readme/USAGE.rst
odoo/addons/purchase_requisition_grouped_by_procurement/static/description/icon.png
odoo/addons/purchase_requisition_grouped_by_procurement/static/description/index.html
odoo/addons/purchase_requisition_grouped_by_procurement/tests/__init__.py
odoo/addons/purchase_requisition_grouped_by_procurement/tests/test_purchase_requisition_grouped_by_procurement.py
odoo_addon_purchase_requisition_grouped_by_procurement-15.0.1.1.1.dist-info/METADATA
odoo_addon_purchase_requisition_grouped_by_procurement-15.0.1.1.1.dist-info/WHEEL
odoo_addon_purchase_requisition_grouped_by_procurement-15.0.1.1.1.dist-info/top_level.txt
odoo_addon_purchase_requisition_grouped_by_procurement-15.0.1.1.1.dist-info/RECORD
