Metadata-Version: 2.1
Name: odoo-addon-purchase_requisition_grouped_by_procurement
Version: 15.0.1.1.1
Summary: Purchase Requisition Grouped by Procurement
Home-page: https://github.com/OCA/purchase-workflow
Author: Tecnativa, Odoo Community Association (OCA)
Author-email: support@odoo-community.org
License: AGPL-3
Classifier: Programming Language :: Python
Classifier: Framework :: Odoo
Classifier: Framework :: Odoo :: 15.0
Classifier: License :: OSI Approved :: GNU Affero General Public License v3
Requires-Python: >=3.8
Requires-Dist: odoo<15.1dev,>=15.0a
